README.rst
setup.py
unittester/__init__.py
unittester.egg-info/PKG-INFO
unittester.egg-info/SOURCES.txt
unittester.egg-info/dependency_links.txt
unittester.egg-info/top_level.txt
unittester.egg-info/zip-safe